pythonTool/__init__.py
pythonTool/db_inspector.py
pythonTool/foreign_key_specification.py
pythonTool/main_app.py
pythonTool/rdf/__init__.py
pythonTool/rdf/annotation_factory.py
pythonTool/rdf/data_factory.py
pythonTool/rdf/ontology_factory.py
pythonTool/rdf/rdf_factory.py
pythonTool/rdf/statement_collector.py
pythonTool/rdf/ontology/__init__.py
pythonTool/rdf/ontology/dbo.py
triplifier-2.2.0.dist-info/licenses/LICENSE
triplifier-2.2.0.dist-info/METADATA
triplifier-2.2.0.dist-info/WHEEL
triplifier-2.2.0.dist-info/entry_points.txt
triplifier-2.2.0.dist-info/top_level.txt
triplifier-2.2.0.dist-info/RECORD
