Metadata-Version: 2.4
Name: triplifier
Version: 2.2.0
Summary: Python port of the Triplifier tool.
Author: Johan van Soest
License:                                  Apache License
Requires-Python: >=3.8
License-File: LICENSE
Requires-Dist: rdflib>=6.0.0
Requires-Dist: PyYAML>=5.3
Requires-Dist: SQLAlchemy>=1.4
Requires-Dist: psycopg2-binary>=2.8
Dynamic: license-file
